hydraspa
