Metadata-Version: 1.0
Name: hydraspa
Version: 0.3.1
Summary: UNKNOWN
Home-page: https://github.com/richardjgowers/hydraspa
Author: Richard J Gowers
Author-email: UNKNOWN
License: GPL v3
Platform: UNKNOWN
